Metadata-Version: 2.1
Name: getRemarks
Version: 0.0.4
Summary: Find grade scored and then remarks regarding the grade
Home-page: UNKNOWN
Author: Seyed Muzaffar
Author-email: iammseyed@protonmail.com
License: UNKNOWN
Platform: UNKNOWN
License-File: LICENSE.txt
